{
  "swagger": "2.0",
  "host": "localhost:10018",
  "basePath": "/",
  "info": {
    "title": "manhuagui-backend",
    "description": "An unofficial backend for manhuagui written in golang/gin",
    "version": "1.0",
    "contact": {
      "name": "Aoi-hosizora",
      "url": "https://github.com/Aoi-hosizora",
      "email": "aoihosizora@hotmail.com"
    }
  },
  "tags": [
    {
      "name": "Manga",
      "description": "manga-controller"
    },
    {
      "name": "Category",
      "description": "category-controller"
    }
  ],
  "paths": {
    "/v1/category/age": {
      "get": {
        "summary": "Get ages",
        "operationId": "-v1-category-age-get",
        "tags": [
          "Category"
        ],
        "responses": {
          "200": {
            "schema": {
              "originRef": "_Result<_Page<CategoryDto>>",
              "$ref": "#/definitions/_Result<_Page<CategoryDto>>"
            }
          }
        }
      }
    },
    "/v1/category/genre": {
      "get": {
        "summary": "Get genres",
        "operationId": "-v1-category-genre-get",
        "tags": [
          "Category"
        ],
        "responses": {
          "200": {
            "schema": {
              "originRef": "_Result<_Page<CategoryDto>>",
              "$ref": "#/definitions/_Result<_Page<CategoryDto>>"
            }
          }
        }
      }
    },
    "/v1/category/genre/{genre}": {
      "get": {
        "summary": "Get genre mangas",
        "operationId": "-v1-category-genre-genre-get",
        "tags": [
          "Category"
        ],
        "parameters": [
          {
            "name": "genre",
            "in": "path",
            "required": true,
            "type": "string",
            "description": "genre name"
          },
          {
            "name": "zone",
            "in": "query",
            "required": false,
            "type": "string",
            "description": "manga zone"
          },
          {
            "name": "age",
            "in": "query",
            "required": false,
            "type": "string",
            "description": "manga age, (shaonv|shaonian|qingnian|ertong|tongyong)"
          },
          {
            "name": "status",
            "in": "query",
            "required": false,
            "type": "string",
            "description": "manga status, (lianzai|wanjie)"
          },
          {
            "name": "page",
            "in": "query",
            "required": false,
            "type": "integer",
            "description": "current page",
            "format": "int32"
          },
          {
            "name": "order",
            "in": "query",
            "required": false,
            "type": "string",
            "description": "order string"
          }
        ],
        "responses": {
          "200": {
            "schema": {
              "originRef": "_Result<_Page<TinyMangaPageDto>>",
              "$ref": "#/definitions/_Result<_Page<TinyMangaPageDto>>"
            }
          }
        }
      }
    },
    "/v1/category/zone": {
      "get": {
        "summary": "Get zones",
        "operationId": "-v1-category-zone-get",
        "tags": [
          "Category"
        ],
        "responses": {
          "200": {
            "schema": {
              "originRef": "_Result<_Page<CategoryDto>>",
              "$ref": "#/definitions/_Result<_Page<CategoryDto>>"
            }
          }
        }
      }
    },
    "/v1/list/finish": {
      "get": {
        "summary": "Get finished mangas",
        "operationId": "-v1-list-finish-get",
        "tags": [
          "Manga"
        ],
        "responses": {
          "200": {
            "schema": {
              "originRef": "_Result<MangaPageGroupListDto>",
              "$ref": "#/definitions/_Result<MangaPageGroupListDto>"
            }
          }
        }
      }
    },
    "/v1/list/latest": {
      "get": {
        "summary": "Get latest mangas",
        "operationId": "-v1-list-latest-get",
        "tags": [
          "Manga"
        ],
        "responses": {
          "200": {
            "schema": {
              "originRef": "_Result<MangaPageGroupListDto>",
              "$ref": "#/definitions/_Result<MangaPageGroupListDto>"
            }
          }
        }
      }
    },
    "/v1/list/serial": {
      "get": {
        "summary": "Get hot serial mangas",
        "operationId": "-v1-list-serial-get",
        "tags": [
          "Manga"
        ],
        "responses": {
          "200": {
            "schema": {
              "originRef": "_Result<MangaPageGroupListDto>",
              "$ref": "#/definitions/_Result<MangaPageGroupListDto>"
            }
          }
        }
      }
    },
    "/v1/list/updated": {
      "get": {
        "summary": "Get latest mangas",
        "operationId": "-v1-list-updated-get",
        "tags": [
          "Manga"
        ],
        "parameters": [
          {
            "name": "page",
            "in": "query",
            "required": false,
            "type": "integer",
            "description": "current page",
            "format": "int32"
          },
          {
            "name": "limit",
            "in": "query",
            "required": false,
            "type": "integer",
            "description": "page size",
            "format": "int32"
          }
        ],
        "responses": {
          "200": {
            "schema": {
              "originRef": "_Result<_Page<TinyMangaPageDto>>",
              "$ref": "#/definitions/_Result<_Page<TinyMangaPageDto>>"
            }
          }
        }
      }
    },
    "/v1/manga": {
      "get": {
        "summary": "Get all manga pages",
        "operationId": "-v1-manga-get",
        "tags": [
          "Manga"
        ],
        "parameters": [
          {
            "name": "page",
            "in": "query",
            "required": false,
            "type": "integer",
            "description": "current page",
            "format": "int32"
          },
          {
            "name": "order",
            "in": "query",
            "required": false,
            "type": "string",
            "description": "order string"
          }
        ],
        "responses": {
          "200": {
            "schema": {
              "originRef": "_Result<_Page<TinyMangaPageDto>>",
              "$ref": "#/definitions/_Result<_Page<TinyMangaPageDto>>"
            }
          }
        }
      }
    },
    "/v1/manga/{mid}": {
      "get": {
        "summary": "Get manga page",
        "operationId": "-v1-manga-mid-get",
        "tags": [
          "Manga"
        ],
        "parameters": [
          {
            "name": "mid",
            "in": "path",
            "required": true,
            "type": "integer",
            "description": "manga id",
            "format": "int64"
          }
        ],
        "responses": {
          "200": {
            "schema": {
              "originRef": "_Result<MangaPageDto>",
              "$ref": "#/definitions/_Result<MangaPageDto>"
            }
          }
        }
      }
    },
    "/v1/manga/{mid}/{cid}": {
      "get": {
        "summary": "Get manga chapter",
        "operationId": "-v1-manga-mid-cid-get",
        "tags": [
          "Manga"
        ],
        "parameters": [
          {
            "name": "mid",
            "in": "path",
            "required": true,
            "type": "integer",
            "description": "manga id",
            "format": "int64"
          },
          {
            "name": "cid",
            "in": "path",
            "required": true,
            "type": "integer",
            "description": "manga chapter id",
            "format": "int64"
          }
        ],
        "responses": {
          "200": {
            "schema": {
              "originRef": "_Result<MangaChapterDto>",
              "$ref": "#/definitions/_Result<MangaChapterDto>"
            }
          }
        }
      }
    }
  },
  "definitions": {
    "CategoryDto": {
      "type": "object",
      "required": [
        "name",
        "title",
        "url"
      ],
      "description": "Category response",
      "properties": {
        "name": {
          "type": "string",
          "required": true,
          "description": "category name"
        },
        "title": {
          "type": "string",
          "required": true,
          "description": "category title"
        },
        "url": {
          "type": "string",
          "required": true,
          "description": "category link"
        }
      }
    },
    "MangaChapterDto": {
      "type": "object",
      "required": [
        "cid",
        "title",
        "mid",
        "manga_title",
        "url",
        "pages",
        "page_count",
        "next_cid",
        "prev_cid"
      ],
      "description": "Mange chapter response",
      "properties": {
        "cid": {
          "type": "integer",
          "required": true,
          "description": "chapter id",
          "format": "int64"
        },
        "title": {
          "type": "string",
          "required": true,
          "description": "chapter name"
        },
        "mid": {
          "type": "integer",
          "required": true,
          "description": "manga id",
          "format": "int64"
        },
        "manga_title": {
          "type": "string",
          "required": true,
          "description": "manga name"
        },
        "url": {
          "type": "string",
          "required": true,
          "description": "chapter link"
        },
        "pages": {
          "type": "array",
          "required": true,
          "description": "chapter pages",
          "items": {
            "type": "string"
          }
        },
        "page_count": {
          "type": "integer",
          "required": true,
          "description": "chapter pages count",
          "format": "int32"
        },
        "next_cid": {
          "type": "integer",
          "required": true,
          "description": "next chapter id",
          "format": "int64"
        },
        "prev_cid": {
          "type": "integer",
          "required": true,
          "description": "prev chapter id",
          "format": "int64"
        }
      }
    },
    "MangaChapterGroupDto": {
      "type": "object",
      "required": [
        "title",
        "chapters"
      ],
      "description": "Mange chapter group response",
      "properties": {
        "title": {
          "type": "string",
          "required": true,
          "description": "group title"
        },
        "chapters": {
          "type": "array",
          "required": true,
          "description": "group chapters",
          "items": {
            "originRef": "TinyMangaChapterDto",
            "$ref": "#/definitions/TinyMangaChapterDto"
          }
        }
      }
    },
    "MangaPageDto": {
      "type": "object",
      "required": [
        "mid",
        "title",
        "cover",
        "url",
        "publish_year",
        "manga_zone",
        "genres",
        "author_name",
        "alias",
        "finished",
        "newest_chapter",
        "newest_date",
        "introduction",
        "manga_rank",
        "average_score",
        "score_count",
        "per_scores",
        "chapter_groups"
      ],
      "description": "Mange page response",
      "properties": {
        "mid": {
          "type": "integer",
          "required": true,
          "description": "manga id",
          "format": "int64"
        },
        "title": {
          "type": "string",
          "required": true,
          "description": "manga name"
        },
        "cover": {
          "type": "string",
          "required": true,
          "description": "manga cover"
        },
        "url": {
          "type": "string",
          "required": true,
          "description": "manga link"
        },
        "publish_year": {
          "type": "string",
          "required": true,
          "description": "manga publish year"
        },
        "manga_zone": {
          "type": "string",
          "required": true,
          "description": "manga zone"
        },
        "genres": {
          "type": "array",
          "required": true,
          "description": "manga genres",
          "items": {
            "originRef": "CategoryDto",
            "$ref": "#/definitions/CategoryDto"
          }
        },
        "author_name": {
          "type": "string",
          "required": true,
          "description": "manga author name"
        },
        "alias": {
          "type": "string",
          "required": true,
          "description": "manga alias name"
        },
        "finished": {
          "type": "boolean",
          "required": true,
          "description": "manga is finished"
        },
        "newest_chapter": {
          "type": "string",
          "required": true,
          "description": "manga last update chapter"
        },
        "newest_date": {
          "type": "string",
          "required": true,
          "description": "manga last update date"
        },
        "introduction": {
          "type": "string",
          "required": true,
          "description": "manga introduction"
        },
        "manga_rank": {
          "type": "string",
          "required": true,
          "description": "manga rank"
        },
        "average_score": {
          "type": "number",
          "required": true,
          "description": "manga average score",
          "format": "float"
        },
        "score_count": {
          "type": "integer",
          "required": true,
          "description": "manga score count",
          "format": "int32"
        },
        "per_scores": {
          "type": "array",
          "required": true,
          "description": "manga per scores, from 0 to 5",
          "items": {
            "type": "number",
            "format": "float"
          }
        },
        "chapter_groups": {
          "type": "array",
          "required": true,
          "description": "manga chapter groups",
          "items": {
            "originRef": "MangaChapterGroupDto",
            "$ref": "#/definitions/MangaChapterGroupDto"
          }
        }
      }
    },
    "MangaPageGroupDto": {
      "type": "object",
      "required": [
        "title",
        "mangas"
      ],
      "description": "Mange page group response",
      "properties": {
        "title": {
          "type": "string",
          "required": true,
          "description": "group title"
        },
        "mangas": {
          "type": "array",
          "required": true,
          "description": "group mangas",
          "items": {
            "originRef": "TinyMangaChapterDto",
            "$ref": "#/definitions/TinyMangaChapterDto"
          }
        }
      }
    },
    "MangaPageGroupListDto": {
      "type": "object",
      "required": [
        "title",
        "top_group",
        "groups",
        "other_groups"
      ],
      "description": "Manga page group list",
      "properties": {
        "title": {
          "type": "string",
          "required": true,
          "description": "list title"
        },
        "top_group": {
          "required": true,
          "description": "manga top page group",
          "originRef": "MangaPageGroupDto",
          "$ref": "#/definitions/MangaPageGroupDto"
        },
        "groups": {
          "type": "array",
          "required": true,
          "description": "manga page groups",
          "items": {
            "originRef": "MangaPageGroupDto",
            "$ref": "#/definitions/MangaPageGroupDto"
          }
        },
        "other_groups": {
          "type": "array",
          "required": true,
          "description": "manga other page groups",
          "items": {
            "originRef": "MangaPageGroupDto",
            "$ref": "#/definitions/MangaPageGroupDto"
          }
        }
      }
    },
    "Result": {
      "type": "object",
      "required": [
        "code",
        "message"
      ],
      "description": "global response",
      "properties": {
        "code": {
          "type": "integer",
          "required": true,
          "description": "status code",
          "format": "int32"
        },
        "message": {
          "type": "string",
          "required": true,
          "description": "status message"
        }
      }
    },
    "TinyMangaChapterDto": {
      "type": "object",
      "required": [
        "cid",
        "title",
        "mid",
        "url",
        "page_count",
        "is_new"
      ],
      "description": "Manga chapter link response",
      "properties": {
        "cid": {
          "type": "integer",
          "required": true,
          "description": "chapter id",
          "format": "int64"
        },
        "title": {
          "type": "string",
          "required": true,
          "description": "chapter name"
        },
        "mid": {
          "type": "integer",
          "required": true,
          "description": "manga id",
          "format": "int64"
        },
        "url": {
          "type": "string",
          "required": true,
          "description": "chapter link"
        },
        "page_count": {
          "type": "integer",
          "required": true,
          "description": "chapter pages count",
          "format": "int32"
        },
        "is_new": {
          "type": "boolean",
          "required": true,
          "description": "chapter is uploaded newly"
        }
      }
    },
    "TinyMangaPageDto": {
      "type": "object",
      "required": [
        "mid",
        "title",
        "cover",
        "url",
        "finished",
        "newest_chapter",
        "newest_date"
      ],
      "description": "Manga page link response",
      "properties": {
        "mid": {
          "type": "integer",
          "required": true,
          "description": "manga id",
          "format": "int64"
        },
        "title": {
          "type": "string",
          "required": true,
          "description": "manga name"
        },
        "cover": {
          "type": "string",
          "required": true,
          "description": "manga cover"
        },
        "url": {
          "type": "string",
          "required": true,
          "description": "manga link"
        },
        "finished": {
          "type": "boolean",
          "required": true,
          "description": "manga is finished"
        },
        "newest_chapter": {
          "type": "string",
          "required": true,
          "description": "manga last update chapter"
        },
        "newest_date": {
          "type": "string",
          "required": true,
          "description": "manga last update date"
        }
      }
    },
    "_Page<CategoryDto>": {
      "type": "object",
      "required": [
        "page",
        "limit",
        "total",
        "data"
      ],
      "description": "page response",
      "properties": {
        "page": {
          "type": "integer",
          "required": true,
          "description": "current page",
          "format": "int32"
        },
        "limit": {
          "type": "integer",
          "required": true,
          "description": "page size",
          "format": "int32"
        },
        "total": {
          "type": "integer",
          "required": true,
          "description": "data count",
          "format": "int32"
        },
        "data": {
          "type": "array",
          "required": true,
          "description": "page data",
          "items": {
            "originRef": "CategoryDto",
            "$ref": "#/definitions/CategoryDto"
          }
        }
      }
    },
    "_Page<TinyMangaPageDto>": {
      "type": "object",
      "required": [
        "page",
        "limit",
        "total",
        "data"
      ],
      "description": "page response",
      "properties": {
        "page": {
          "type": "integer",
          "required": true,
          "description": "current page",
          "format": "int32"
        },
        "limit": {
          "type": "integer",
          "required": true,
          "description": "page size",
          "format": "int32"
        },
        "total": {
          "type": "integer",
          "required": true,
          "description": "data count",
          "format": "int32"
        },
        "data": {
          "type": "array",
          "required": true,
          "description": "page data",
          "items": {
            "originRef": "TinyMangaPageDto",
            "$ref": "#/definitions/TinyMangaPageDto"
          }
        }
      }
    },
    "_Result<MangaChapterDto>": {
      "type": "object",
      "required": [
        "code",
        "message",
        "data"
      ],
      "description": "global response",
      "properties": {
        "code": {
          "type": "integer",
          "required": true,
          "description": "status code",
          "format": "int32"
        },
        "message": {
          "type": "string",
          "required": true,
          "description": "status message"
        },
        "data": {
          "required": true,
          "description": "response data",
          "originRef": "MangaChapterDto",
          "$ref": "#/definitions/MangaChapterDto"
        }
      }
    },
    "_Result<MangaPageDto>": {
      "type": "object",
      "required": [
        "code",
        "message",
        "data"
      ],
      "description": "global response",
      "properties": {
        "code": {
          "type": "integer",
          "required": true,
          "description": "status code",
          "format": "int32"
        },
        "message": {
          "type": "string",
          "required": true,
          "description": "status message"
        },
        "data": {
          "required": true,
          "description": "response data",
          "originRef": "MangaPageDto",
          "$ref": "#/definitions/MangaPageDto"
        }
      }
    },
    "_Result<MangaPageGroupListDto>": {
      "type": "object",
      "required": [
        "code",
        "message",
        "data"
      ],
      "description": "global response",
      "properties": {
        "code": {
          "type": "integer",
          "required": true,
          "description": "status code",
          "format": "int32"
        },
        "message": {
          "type": "string",
          "required": true,
          "description": "status message"
        },
        "data": {
          "required": true,
          "description": "response data",
          "originRef": "MangaPageGroupListDto",
          "$ref": "#/definitions/MangaPageGroupListDto"
        }
      }
    },
    "_Result<_Page<CategoryDto>>": {
      "type": "object",
      "required": [
        "code",
        "message",
        "data"
      ],
      "description": "global response",
      "properties": {
        "code": {
          "type": "integer",
          "required": true,
          "description": "status code",
          "format": "int32"
        },
        "message": {
          "type": "string",
          "required": true,
          "description": "status message"
        },
        "data": {
          "required": true,
          "description": "response data",
          "originRef": "_Page\u003cCategoryDto\u003e",
          "$ref": "#/definitions/_Page\u003cCategoryDto\u003e"
        }
      }
    },
    "_Result<_Page<TinyMangaPageDto>>": {
      "type": "object",
      "required": [
        "code",
        "message",
        "data"
      ],
      "description": "global response",
      "properties": {
        "code": {
          "type": "integer",
          "required": true,
          "description": "status code",
          "format": "int32"
        },
        "message": {
          "type": "string",
          "required": true,
          "description": "status message"
        },
        "data": {
          "required": true,
          "description": "response data",
          "originRef": "_Page\u003cTinyMangaPageDto\u003e",
          "$ref": "#/definitions/_Page\u003cTinyMangaPageDto\u003e"
        }
      }
    }
  }
}
